Workbook

Sheet Shariah
F1: =iferror(Sheet1!B4,"") -> Mindteck (India) Ltd
B3: Stock Code | D3: mindteck | F3: =IFERROR("Cmp: "& Sheet1!B3,"") -> Cmp: 178 | H3: =IFERROR("Industry : "& Sheet1!H84,"") | N3: =IFERROR("Sector : "& Sheet1!H85,"") -> Sector : Information Technology
B5: Market Cap | D5: =IFERROR( int(Sheet1!F79),"") -> 543 | F5: =if(D3<>"", IFERROR("Business : "& Sheet1!G92,""),"") -> Business : Pass | H5: =IFERROR("Business Overview : "& char(10) &Sheet1!H86,"") -> Business Overview : Incorporated in 1991, Mindteck Ltd is in the business of rendering engineering and IT services
B7: Non-Sharia Income | D7: =IF(Sheet1!G92="Fail","",iferror(Sheet1!G7,"")) -> 1.7199017 | F7: =iferror(IF(Sheet1!G92="Fail","",Sheet1!H7),"") -> Pass
B9: Debt/Total Assets | D9: =IF(Sheet1!G92="Fail","",iferror(Sheet1!E68,"")) -> 1.0810811 | F9: =iferror(IF(Sheet1!G92="Fail","",Sheet1!F68),"") -> Pass
B11: Illiquidit Assets | D11: =IF(Sheet1!G92="Fail","",iferror(Sheet1!E71,"")) -> 8.9189189 | F11: =iferror(IF(Sheet1!G92="Fail","",Sheet1!F71),"") -> Fail
B13: Liquid Assets | F13: =iferror(IF(Sheet1!G92="Fail","",Sheet1!H78),"") -> Pass
B15: Inventories | F15: =IFERROR("Stock Shariah Status : "& Sheet1!G93,"") -> Stock Shariah Status : Non-Compliant
H17: =iferror(Data!F4,"")
B20: Manual Shariah Calculator:
B21: Non-Sharia Income | D21: =iferror(SUM(D23,D25,D27,D29)/D31*100,"") | F21: Debt/Total Assets | H21: =iferror(((H23+H25)-H27)/H29*100,"") | J21: Illiquid Asset Ratio | L21: =iferror(SUM(L23,L25,L27,L29,L31)/H29*100,"") | N21: Liquid Asset to Mcap | P21: =if(H29-SUM(L23,L25,L27,L29,L31)-P23=0,"",IFERROR(H29-SUM(L23,L25,L27,L29,L31)-P23,"")) | R21: Profit/Divident
B23: from Non-sharia Sales | F23: Non-current borrowing | J23: Property, Plant & Equipment | N23: Total Liabilities | R23: =if(Sheet1!G93<> "Compliant","",iferror(if(AND(T25<>"",T21<>""),("Donate Divident/Profit Rs."&int(T25%*T21)),""),""))
B25: Interest Income | F25: Current borrowing | J25: CWIP | T25: =IF(D21<>"",D21,D7) -> 1.7199017
B27: Any other Investment | F27: Non-Interest loan | I27: ` | J27: Inventories | N27: *Calculations are based on the Fatwa of Mufti Taqi Usmani. **Please perform your own calculations in the part below before making any decisions as the findings from the above section's auto calculation may not be accurate. Donate as much as you can to the needy!
B29: Any Non-Sharia Income | F29: Total Assets | J29: Intangible Assets
B31: Total Sales/Revenue | J31: Right of use/goodwill

Sheet Sheet19

Sheet Sheet1
A1: =Shariah!D3 -> mindteck | C1: //*[@id="top-ratios"]/li[2]/span[2]/span | F1: //*[@id="top"]/div[1]/div/h1
A2: inventory | B2: =Shariah!D15
A3: cmp | B3: =IFERROR(__xludf.DUMMYFUNCTION("IMPORTXML(B5,C1)"),178.0) -> 178
A4: name | B4: =IFERROR(__xludf.DUMMYFUNCTION("IMPORTXML(B5,F1)"),"Mindteck (India) Ltd") -> Mindteck (India) Ltd
A5: ="https://www.screener.in/company/"&A1&"/consolidated/" -> https://www.screener.in/company/mindteck/consolidated/ | B5: ="https://www.screener.in/company/"&A1&"/" -> https://www.screener.in/company/mindteck/
A6: date | B6: {=INDEX(11:11, 1, MAX(IF(11:11<>"", COLUMN(11:11)-1, 0)))} -> Mar 2026 | C6: {=trim(INDEX(11:11, 1, MAX(IF(11:11<>"", COLUMN(11:11), 0))))} -> TTM | D6: Final value | E6: Interest or Other | F6: Ratio
A7: Other Income | B7: {=INDEX(INDIRECT(D10 & ":" & D10), 1, MAX(IF(INDIRECT(D10 & ":" & D10)<>"", COLUMN(INDIRECT(D10 & ":" & D10))-1, 0)))} -> 7 | C7: {=INDEX(INDIRECT(D10 & ":" & D10), 1, MAX(IF(INDIRECT(D10 & ":" & D10)<>"", COLUMN(INDIRECT(D10 & ":" & D10)), 0)))} -> 7 | D7: =IF($C$6="TTM", B7,C7) -> 7 | E7: =IF(D7<=0,D8,D7) -> 7 | F7: =E7/D9*100 -> 1.7199017 | G7: =IF(ISERROR(F7),F26,F7) -> 1.7199017 | H7: =if(G7<=5, "Pass","Fail") -> Pass
A8: Interest | B8: {=INDEX(INDIRECT(C10 & ":" & C10), 1, MAX(IF(INDIRECT(C10 & ":" & C10)<>"", COLUMN(INDIRECT(C10 & ":" & C10))-1, 0)))} -> 1 | C8: {=INDEX(INDIRECT(C10 & ":" & C10), 1, MAX(IF(INDIRECT(C10 & ":" & C10)<>"", COLUMN(INDIRECT(C10 & ":" & C10)), 0)))} -> 1 | D8: =IF($C$6="TTM", B8,C8) -> 1
A9: Sales | B9: {=INDEX(INDIRECT(B10 & ":" & B10), 1, MAX(IF(INDIRECT(B10 & ":" & B10)<>"", COLUMN(INDIRECT(B10 & ":" & B10))-1, 0)))} -> 407 | C9: {=INDEX(INDIRECT(B10 & ":" & B10), 1, MAX(IF(INDIRECT(B10 & ":" & B10)<>"", COLUMN(INDIRECT(B10 & ":" & B10)), 0)))} -> 410 | D9: =IF($C$6="TTM", B9,C9) -> 407
A10: row number | B10: =iferror(row()+match("Sales +",A12:A23, 0)+1,E10) -> 12 | C10: =row()+match("Interest",A12:A23, 0)+1 -> 17 | D10: =row()+match("Other Income +",A12:A23, 0)+1 -> 16 | E10: =row()+match("Revenue",A12:A23, 0)+1 -> #N/A
A11: =IFERROR(__xludf.DUMMYFUNCTION("query(IMPORTHTML($A$5,""table"",2),""SELECT *"",1)"),"") | B11: =IFERROR(__xludf.DUMMYFUNCTION("""COMPUTED_VALUE"""),"Mar 2015") -> Mar 2015 | C11: =IFERROR(__xludf.DUMMYFUNCTION("""COMPUTED_VALUE"""),"Mar 2016") -> Mar 2016 | D11: =IFERROR(__xludf.DUMMYFUNCTION("""COMPUTED_VALUE"""),"Mar 2017") -> Mar 2017 | E11: =IFERROR(__xludf.DUMMYFUNCTION("""COMPUTED_VALUE"""),"Mar 2018") -> Mar 2018 | F11: =IFERROR(__xludf.DUMMYFUNCTION("""COMPUTED_VALUE"""),"Mar 2019") -> Mar 2019 | G11: =IFERROR(__xludf.DUMMYFUNCTION("""COMPUTED_VALUE"""),"Mar 2020") -> Mar 2020 | H11: =IFERROR(__xludf.DUMMYFUNCTION("""COMPUTED_VALUE"""),"Mar 2021") -> Mar 2021 | I11: =IFERROR(__xludf.DUMMYFUNCTION("""COMPUTED_VALUE"""),"Mar 2022") -> Mar 2022 | J11: =IFERROR(__xludf.DUMMYFUNCTION("""COMPUTED_VALUE"""),"Mar 2023") -> Mar 2023 | K11: =IFERROR(__xludf.DUMMYFUNCTION("""COMPUTED_VALUE"""),"Mar 2024") -> Mar 2024 | L11: =IFERROR(__xludf.DUMMYFUNCTION("""COMPUTED_VALUE"""),"Mar 2025") -> Mar 2025 | M11: =IFERROR(__xludf.DUMMYFUNCTION("""COMPUTED_VALUE"""),"Mar 2026") -> Mar 2026 | N11: =IFERROR(__xludf.DUMMYFUNCTION("""COMPUTED_VALUE"""),"TTM") -> TTM
A12: =IFERROR(__xludf.DUMMYFUNCTION("""COMPUTED_VALUE"""),"Sales +") -> Sales + | B12: =IFERROR(__xludf.DUMMYFUNCTION("""COMPUTED_VALUE"""),319.0) -> 319 | C12: =IFERROR(__xludf.DUMMYFUNCTION("""COMPUTED_VALUE"""),312.0) -> 312 | D12: =IFERROR(__xludf.DUMMYFUNCTION("""COMPUTED_VALUE"""),342.0) -> 342 | E12: =IFERROR(__xludf.DUMMYFUNCTION("""COMPUTED_VALUE"""),297.0) -> 297 | F12: =IFERROR(__xludf.DUMMYFUNCTION("""COMPUTED_VALUE"""),299.0) -> 299 | G12: =IFERROR(__xludf.DUMMYFUNCTION("""COMPUTED_VALUE"""),276.0) -> 276 | H12: =IFERROR(__xludf.DUMMYFUNCTION("""COMPUTED_VALUE"""),287.0) -> 287 | I12: =IFERROR(__xludf.DUMMYFUNCTION("""COMPUTED_VALUE"""),299.0) -> 299 | J12: =IFERROR(__xludf.DUMMYFUNCTION("""COMPUTED_VALUE"""),337.0) -> 337 | K12: =IFERROR(__xludf.DUMMYFUNCTION("""COMPUTED_VALUE"""),386.0) -> 386 | L12: =IFERROR(__xludf.DUMMYFUNCTION("""COMPUTED_VALUE"""),424.0) -> 424 | M12: =IFERROR(__xludf.DUMMYFUNCTION("""COMPUTED_VALUE"""),407.0) -> 407 | N12: =IFERROR(__xludf.DUMMYFUNCTION("""COMPUTED_VALUE"""),410.0) -> 410
A13: =IFERROR(__xludf.DUMMYFUNCTION("""COMPUTED_VALUE"""),"Expenses +") -> Expenses + | B13: =IFERROR(__xludf.DUMMYFUNCTION("""COMPUTED_VALUE"""),290.0) -> 290 | C13: =IFERROR(__xludf.DUMMYFUNCTION("""COMPUTED_VALUE"""),291.0) -> 291 | D13: =IFERROR(__xludf.DUMMYFUNCTION("""COMPUTED_VALUE"""),331.0) -> 331 | E13: =IFERROR(__xludf.DUMMYFUNCTION("""COMPUTED_VALUE"""),296.0) -> 296 | F13: =IFERROR(__xludf.DUMMYFUNCTION("""COMPUTED_VALUE"""),295.0) -> 295 | G13: =IFERROR(__xludf.DUMMYFUNCTION("""COMPUTED_VALUE"""),272.0) -> 272 | H13: =IFERROR(__xludf.DUMMYFUNCTION("""COMPUTED_VALUE"""),267.0) -> 267 | I13: =IFERROR(__xludf.DUMMYFUNCTION("""COMPUTED_VALUE"""),278.0) -> 278 | J13: =IFERROR(__xludf.DUMMYFUNCTION("""COMPUTED_VALUE"""),310.0) -> 310 | K13: =IFERROR(__xludf.DUMMYFUNCTION("""COMPUTED_VALUE"""),353.0) -> 353 | L13: =IFERROR(__xludf.DUMMYFUNCTION("""COMPUTED_VALUE"""),389.0) -> 389 | M13: =IFERROR(__xludf.DUMMYFUNCTION("""COMPUTED_VALUE"""),369.0) -> 369 | N13: =IFERROR(__xludf.DUMMYFUNCTION("""COMPUTED_VALUE"""),374.0) -> 374
A14: =IFERROR(__xludf.DUMMYFUNCTION("""COMPUTED_VALUE"""),"Operating Profit") -> Operating Profit | B14: =IFERROR(__xludf.DUMMYFUNCTION("""COMPUTED_VALUE"""),29.0) -> 29 | C14: =IFERROR(__xludf.DUMMYFUNCTION("""COMPUTED_VALUE"""),21.0) -> 21 | D14: =IFERROR(__xludf.DUMMYFUNCTION("""COMPUTED_VALUE"""),11.0) -> 11 | E14: =IFERROR(__xludf.DUMMYFUNCTION("""COMPUTED_VALUE"""),1.0) -> 1 | F14: =IFERROR(__xludf.DUMMYFUNCTION("""COMPUTED_VALUE"""),4.0) -> 4 | G14: =IFERROR(__xludf.DUMMYFUNCTION("""COMPUTED_VALUE"""),4.0) -> 4 | H14: =IFERROR(__xludf.DUMMYFUNCTION("""COMPUTED_VALUE"""),20.0) -> 20 | I14: =IFERROR(__xludf.DUMMYFUNCTION("""COMPUTED_VALUE"""),21.0) -> 21 | J14: =IFERROR(__xludf.DUMMYFUNCTION("""COMPUTED_VALUE"""),27.0) -> 27 | K14: =IFERROR(__xludf.DUMMYFUNCTION("""COMPUTED_VALUE"""),32.0) -> 32 | L14: =IFERROR(__xludf.DUMMYFUNCTION("""COMPUTED_VALUE"""),35.0) -> 35 | M14: =IFERROR(__xludf.DUMMYFUNCTION("""COMPUTED_VALUE"""),38.0) -> 38 | N14: =IFERROR(__xludf.DUMMYFUNCTION("""COMPUTED_VALUE"""),36.0) -> 36
A15: =IFERROR(__xludf.DUMMYFUNCTION("""COMPUTED_VALUE"""),"OPM %") -> OPM % | B15: =IFERROR(__xludf.DUMMYFUNCTION("""COMPUTED_VALUE"""),0.09) -> 0.09 | C15: =IFERROR(__xludf.DUMMYFUNCTION("""COMPUTED_VALUE"""),0.07) -> 0.07 | D15: =IFERROR(__xludf.DUMMYFUNCTION("""COMPUTED_VALUE"""),0.032) -> 0.032 | E15: =IFERROR(__xludf.DUMMYFUNCTION("""COMPUTED_VALUE"""),0.004) -> 0.004 | F15: =IFERROR(__xludf.DUMMYFUNCTION("""COMPUTED_VALUE"""),0.015) -> 0.015 | G15: =IFERROR(__xludf.DUMMYFUNCTION("""COMPUTED_VALUE"""),0.016) -> 0.016 | H15: =IFERROR(__xludf.DUMMYFUNCTION("""COMPUTED_VALUE"""),0.07) -> 0.07 | I15: =IFERROR(__xludf.DUMMYFUNCTION("""COMPUTED_VALUE"""),0.07) -> 0.07 | J15: =IFERROR(__xludf.DUMMYFUNCTION("""COMPUTED_VALUE"""),0.08) -> 0.08 | K15: =IFERROR(__xludf.DUMMYFUNCTION("""COMPUTED_VALUE"""),0.08) -> 0.08 | L15: =IFERROR(__xludf.DUMMYFUNCTION("""COMPUTED_VALUE"""),0.08) -> 0.08 | M15: =IFERROR(__xludf.DUMMYFUNCTION("""COMPUTED_VALUE"""),0.09) -> 0.09 | N15: =IFERROR(__xludf.DUMMYFUNCTION("""COMPUTED_VALUE"""),0.09) -> 0.09
A16: =IFERROR(__xludf.DUMMYFUNCTION("""COMPUTED_VALUE"""),"Other Income +") -> Other Income + | B16: =IFERROR(__xludf.DUMMYFUNCTION("""COMPUTED_VALUE"""),1.0) -> 1 | C16: =IFERROR(__xludf.DUMMYFUNCTION("""COMPUTED_VALUE"""),2.0) -> 2 | D16: =IFERROR(__xludf.DUMMYFUNCTION("""COMPUTED_VALUE"""),3.0) -> 3 | E16: =IFERROR(__xludf.DUMMYFUNCTION("""COMPUTED_VALUE"""),0.0) -> 0 | F16: =IFERROR(__xludf.DUMMYFUNCTION("""COMPUTED_VALUE"""),3.0) -> 3 | G16: =IFERROR(__xludf.DUMMYFUNCTION("""COMPUTED_VALUE"""),-59.0) -> -59 | H16: =IFERROR(__xludf.DUMMYFUNCTION("""COMPUTED_VALUE"""),5.0) -> 5 | I16: =IFERROR(__xludf.DUMMYFUNCTION("""COMPUTED_VALUE"""),23.0) -> 23 | J16: =IFERROR(__xludf.DUMMYFUNCTION("""COMPUTED_VALUE"""),4.0) -> 4 | K16: =IFERROR(__xludf.DUMMYFUNCTION("""COMPUTED_VALUE"""),6.0) -> 6 | L16: =IFERROR(__xludf.DUMMYFUNCTION("""COMPUTED_VALUE"""),6.0) -> 6 | M16: =IFERROR(__xludf.DUMMYFUNCTION("""COMPUTED_VALUE"""),7.0) -> 7 | N16: =IFERROR(__xludf.DUMMYFUNCTION("""COMPUTED_VALUE"""),7.0) -> 7
A17: =IFERROR(__xludf.DUMMYFUNCTION("""COMPUTED_VALUE"""),"Interest") -> Interest | B17: =IFERROR(__xludf.DUMMYFUNCTION("""COMPUTED_VALUE"""),0.0) -> 0 | C17: =IFERROR(__xludf.DUMMYFUNCTION("""COMPUTED_VALUE"""),0.0) -> 0 | D17: =IFERROR(__xludf.DUMMYFUNCTION("""COMPUTED_VALUE"""),0.0) -> 0 | E17: =IFERROR(__xludf.DUMMYFUNCTION("""COMPUTED_VALUE"""),1.0) -> 1 | F17: =IFERROR(__xludf.DUMMYFUNCTION("""COMPUTED_VALUE"""),1.0) -> 1 | G17: =IFERROR(__xludf.DUMMYFUNCTION("""COMPUTED_VALUE"""),2.0) -> 2 | H17: =IFERROR(__xludf.DUMMYFUNCTION("""COMPUTED_VALUE"""),2.0) -> 2 | I17: =IFERROR(__xludf.DUMMYFUNCTION("""COMPUTED_VALUE"""),1.0) -> 1 | J17: =IFERROR(__xludf.DUMMYFUNCTION("""COMPUTED_VALUE"""),1.0) -> 1 | K17: =IFERROR(__xludf.DUMMYFUNCTION("""COMPUTED_VALUE"""),1.0) -> 1 | L17: =IFERROR(__xludf.DUMMYFUNCTION("""COMPUTED_VALUE"""),1.0) -> 1 | M17: =IFERROR(__xludf.DUMMYFUNCTION("""COMPUTED_VALUE"""),1.0) -> 1 | N17: =IFERROR(__xludf.DUMMYFUNCTION("""COMPUTED_VALUE"""),1.0) -> 1
A18: =IFERROR(__xludf.DUMMYFUNCTION("""COMPUTED_VALUE"""),"Depreciation") -> Depreciation | B18: =IFERROR(__xludf.DUMMYFUNCTION("""COMPUTED_VALUE"""),2.0) -> 2 | C18: =IFERROR(__xludf.DUMMYFUNCTION("""COMPUTED_VALUE"""),2.0) -> 2 | D18: =IFERROR(__xludf.DUMMYFUNCTION("""COMPUTED_VALUE"""),2.0) -> 2 | E18: =IFERROR(__xludf.DUMMYFUNCTION("""COMPUTED_VALUE"""),1.0) -> 1 | F18: =IFERROR(__xludf.DUMMYFUNCTION("""COMPUTED_VALUE"""),2.0) -> 2 | G18: =IFERROR(__xludf.DUMMYFUNCTION("""COMPUTED_VALUE"""),7.0) -> 7 | H18: =IFERROR(__xludf.DUMMYFUNCTION("""COMPUTED_VALUE"""),6.0) -> 6 | I18: =IFERROR(__xludf.DUMMYFUNCTION("""COMPUTED_VALUE"""),5.0) -> 5 | J18: =IFERROR(__xludf.DUMMYFUNCTION("""COMPUTED_VALUE"""),5.0) -> 5 | K18: =IFERROR(__xludf.DUMMYFUNCTION("""COMPUTED_VALUE"""),4.0) -> 4 | L18: =IFERROR(__xludf.DUMMYFUNCTION("""COMPUTED_VALUE"""),5.0) -> 5 | M18: =IFERROR(__xludf.DUMMYFUNCTION("""COMPUTED_VALUE"""),5.0) -> 5 | N18: =IFERROR(__xludf.DUMMYFUNCTION("""COMPUTED_VALUE"""),5.0) -> 5
A19: =IFERROR(__xludf.DUMMYFUNCTION("""COMPUTED_VALUE"""),"Profit before tax") -> Profit before tax | B19: =IFERROR(__xludf.DUMMYFUNCTION("""COMPUTED_VALUE"""),28.0) -> 28 | C19: =IFERROR(__xludf.DUMMYFUNCTION("""COMPUTED_VALUE"""),21.0) -> 21 | D19: =IFERROR(__xludf.DUMMYFUNCTION("""COMPUTED_VALUE"""),11.0) -> 11 | E19: =IFERROR(__xludf.DUMMYFUNCTION("""COMPUTED_VALUE"""),0.0) -> 0 | F19: =IFERROR(__xludf.DUMMYFUNCTION("""COMPUTED_VALUE"""),4.0) -> 4 | G19: =IFERROR(__xludf.DUMMYFUNCTION("""COMPUTED_VALUE"""),-64.0) -> -64 | H19: =IFERROR(__xludf.DUMMYFUNCTION("""COMPUTED_VALUE"""),16.0) -> 16 | I19: =IFERROR(__xludf.DUMMYFUNCTION("""COMPUTED_VALUE"""),38.0) -> 38 | J19: =IFERROR(__xludf.DUMMYFUNCTION("""COMPUTED_VALUE"""),26.0) -> 26 | K19: =IFERROR(__xludf.DUMMYFUNCTION("""COMPUTED_VALUE"""),34.0) -> 34 | L19: =IFERROR(__xludf.DUMMYFUNCTION("""COMPUTED_VALUE"""),35.0) -> 35 | M19: =IFERROR(__xludf.DUMMYFUNCTION("""COMPUTED_VALUE"""),39.0) -> 39 | N19: =IFERROR(__xludf.DUMMYFUNCTION("""COMPUTED_VALUE"""),38.0) -> 38
A20: =IFERROR(__xludf.DUMMYFUNCTION("""COMPUTED_VALUE"""),"Tax %") -> Tax % | B20: =IFERROR(__xludf.DUMMYFUNCTION("""COMPUTED_VALUE"""),0.31) -> 0.31 | C20: =IFERROR(__xludf.DUMMYFUNCTION("""COMPUTED_VALUE"""),-0.25) -> -0.25 | D20: =IFERROR(__xludf.DUMMYFUNCTION("""COMPUTED_VALUE"""),0.19) -> 0.19 | E20: =IFERROR(__xludf.DUMMYFUNCTION("""COMPUTED_VALUE"""),46.08) -> 46.08 | F20: =IFERROR(__xludf.DUMMYFUNCTION("""COMPUTED_VALUE"""),0.37) -> 0.37 | G20: =IFERROR(__xludf.DUMMYFUNCTION("""COMPUTED_VALUE"""),0.01) -> 0.01 | H20: =IFERROR(__xludf.DUMMYFUNCTION("""COMPUTED_VALUE"""),0.33) -> 0.33 | I20: =IFERROR(__xludf.DUMMYFUNCTION("""COMPUTED_VALUE"""),0.13) -> 0.13 | J20: =IFERROR(__xludf.DUMMYFUNCTION("""COMPUTED_VALUE"""),0.2) -> 0.2 | K20: =IFERROR(__xludf.DUMMYFUNCTION("""COMPUTED_VALUE"""),0.19) -> 0.19 | L20: =IFERROR(__xludf.DUMMYFUNCTION("""COMPUTED_VALUE"""),0.19) -> 0.19 | M20: =IFERROR(__xludf.DUMMYFUNCTION("""COMPUTED_VALUE"""),0.19) -> 0.19
A21: =IFERROR(__xludf.DUMMYFUNCTION("""COMPUTED_VALUE"""),"Net Profit +") -> Net Profit + | B21: =IFERROR(__xludf.DUMMYFUNCTION("""COMPUTED_VALUE"""),19.0) -> 19 | C21: =IFERROR(__xludf.DUMMYFUNCTION("""COMPUTED_VALUE"""),26.0) -> 26 | D21: =IFERROR(__xludf.DUMMYFUNCTION("""COMPUTED_VALUE"""),9.0) -> 9 | E21: =IFERROR(__xludf.DUMMYFUNCTION("""COMPUTED_VALUE"""),-6.0) -> -6 | F21: =IFERROR(__xludf.DUMMYFUNCTION("""COMPUTED_VALUE"""),3.0) -> 3 | G21: =IFERROR(__xludf.DUMMYFUNCTION("""COMPUTED_VALUE"""),-65.0) -> -65 | H21: =IFERROR(__xludf.DUMMYFUNCTION("""COMPUTED_VALUE"""),11.0) -> 11 | I21: =IFERROR(__xludf.DUMMYFUNCTION("""COMPUTED_VALUE"""),33.0) -> 33 | J21: =IFERROR(__xludf.DUMMYFUNCTION("""COMPUTED_VALUE"""),21.0) -> 21 | K21: =IFERROR(__xludf.DUMMYFUNCTION("""COMPUTED_VALUE"""),27.0) -> 27 | L21: =IFERROR(__xludf.DUMMYFUNCTION("""COMPUTED_VALUE"""),29.0) -> 29 | M21: =IFERROR(__xludf.DUMMYFUNCTION("""COMPUTED_VALUE"""),32.0) -> 32 | N21: =IFERROR(__xludf.DUMMYFUNCTION("""COMPUTED_VALUE"""),31.0) -> 31
A22: =IFERROR(__xludf.DUMMYFUNCTION("""COMPUTED_VALUE"""),"EPS in Rs") -> EPS in Rs | B22: =IFERROR(__xludf.DUMMYFUNCTION("""COMPUTED_VALUE"""),6.13) -> 6.13 | C22: =IFERROR(__xludf.DUMMYFUNCTION("""COMPUTED_VALUE"""),8.23) -> 8.23 | D22: =IFERROR(__xludf.DUMMYFUNCTION("""COMPUTED_VALUE"""),2.93) -> 2.93 | E22: =IFERROR(__xludf.DUMMYFUNCTION("""COMPUTED_VALUE"""),-1.77) -> -1.77 | F22: =IFERROR(__xludf.DUMMYFUNCTION("""COMPUTED_VALUE"""),0.86) -> 0.86 | G22: =IFERROR(__xludf.DUMMYFUNCTION("""COMPUTED_VALUE"""),-20.25) -> -20.25 | H22: =IFERROR(__xludf.DUMMYFUNCTION("""COMPUTED_VALUE"""),3.39) -> 3.39 | I22: =IFERROR(__xludf.DUMMYFUNCTION("""COMPUTED_VALUE"""),10.38) -> 10.38 | J22: =IFERROR(__xludf.DUMMYFUNCTION("""COMPUTED_VALUE"""),6.57) -> 6.57 | K22: =IFERROR(__xludf.DUMMYFUNCTION("""COMPUTED_VALUE"""),8.62) -> 8.62 | L22: =IFERROR(__xludf.DUMMYFUNCTION("""COMPUTED_VALUE"""),8.99) -> 8.99 | M22: =IFERROR(__xludf.DUMMYFUNCTION("""COMPUTED_VALUE"""),9.86) -> 9.86 | N22: =IFERROR(__xludf.DUMMYFUNCTION("""COMPUTED_VALUE"""),9.75) -> 9.75
A23: =IFERROR(__xludf.DUMMYFUNCTION("""COMPUTED_VALUE"""),"Dividend Payout %") -> Dividend Payout % | B23: =IFERROR(__xludf.DUMMYFUNCTION("""COMPUTED_VALUE"""),0.13) -> 0.13 | C23: =IFERROR(__xludf.DUMMYFUNCTION("""COMPUTED_VALUE"""),0.1) -> 0.1 | D23: =IFERROR(__xludf.DUMMYFUNCTION("""COMPUTED_VALUE"""),0.27) -> 0.27 | E23: =IFERROR(__xludf.DUMMYFUNCTION("""COMPUTED_VALUE"""),-0.45) -> -0.45 | F23: =IFERROR(__xludf.DUMMYFUNCTION("""COMPUTED_VALUE"""),0.92) -> 0.92 | G23: =IFERROR(__xludf.DUMMYFUNCTION("""COMPUTED_VALUE"""),0.0) -> 0 | H23: =IFERROR(__xludf.DUMMYFUNCTION("""COMPUTED_VALUE"""),0.0) -> 0 | I23: =IFERROR(__xludf.DUMMYFUNCTION("""COMPUTED_VALUE"""),0.08) -> 0.08 | J23: =IFERROR(__xludf.DUMMYFUNCTION("""COMPUTED_VALUE"""),0.12) -> 0.12 | K23: =IFERROR(__xludf.DUMMYFUNCTION("""COMPUTED_VALUE"""),0.09) -> 0.09 | L23: =IFERROR(__xludf.DUMMYFUNCTION("""COMPUTED_VALUE"""),0.11) -> 0.11 | M23: =IFERROR(__xludf.DUMMYFUNCTION("""COMPUTED_VALUE"""),0.1) -> 0.1
A25: date | B25: {=INDEX(30:30, 1, MAX(IF(30:30<>"", COLUMN(30:30)-1, 0)))} -> Mar 2026 | C25: {=trim(INDEX(30:30, 1, MAX(IF(30:30<>"", COLUMN(30:30), 0))))} -> TTM | D25: Final value | E25: Interest or Other | F25: Ratio
A26: Other Income | B26: {=INDEX(INDIRECT(D29 & ":" & D29), 1, MAX(IF(INDIRECT(D29 & ":" & D29)<>"", COLUMN(INDIRECT(D29 & ":" & D29))-1, 0)))} -> 3 | C26: {=INDEX(INDIRECT(D29 & ":" & D29), 1, MAX(IF(INDIRECT(D29 & ":" & D29)<>"", COLUMN(INDIRECT(D29 & ":" & D29)), 0)))} -> 3 | D26: =IF($C$25="TTM", B26,C26) -> 3 | E26: =IF(D26<=0,D27,D26) -> 3 | F26: =E26/D28*100 -> 2
A27: Interest | B27: {=INDEX(INDIRECT(C29 & ":" & C29), 1, MAX(IF(INDIRECT(C29 & ":" & C29)<>"", COLUMN(INDIRECT(C29 & ":" & C29))-1, 0)))} -> 1 | C27: {=INDEX(INDIRECT(C29 & ":" & C29), 1, MAX(IF(INDIRECT(C29 & ":" & C29)<>"", COLUMN(INDIRECT(C29 & ":" & C29)), 0)))} -> 0 | D27: =IF($C$25="TTM", B27,C27) -> 1
A28: Sales | B28: {=INDEX(INDIRECT(B29 & ":" & B29), 1, MAX(IF(INDIRECT(B29 & ":" & B29)<>"", COLUMN(INDIRECT(B29 & ":" & B29))-1, 0)))} -> 150 | C28: {=INDEX(INDIRECT(B29 & ":" & B29), 1, MAX(IF(INDIRECT(B29 & ":" & B29)<>"", COLUMN(INDIRECT(B29 & ":" & B29)), 0)))} -> 148 | D28: =IF($C$25="TTM", B28,C28) -> 150
B29: =iferror(row()+match("Sales +",A31:A42, 0)+1,E29) -> 31 | C29: =row()+match("Interest",A31:A42, 0)+1 -> 36 | D29: =row()+match("Other Income +",A31:A42, 0)+1 -> 35 | E29: =row()+match("Revenue",A31:A42, 0)+1 -> #N/A
A30: =IFERROR(__xludf.DUMMYFUNCTION("query(IMPORTHTML($B$5,""table"",2),""SELECT *"",1)"),"") | B30: =IFERROR(__xludf.DUMMYFUNCTION("""COMPUTED_VALUE"""),"Mar 2015") -> Mar 2015 | C30: =IFERROR(__xludf.DUMMYFUNCTION("""COMPUTED_VALUE"""),"Mar 2016") -> Mar 2016 | D30: =IFERROR(__xludf.DUMMYFUNCTION("""COMPUTED_VALUE"""),"Mar 2017") -> Mar 2017 | E30: =IFERROR(__xludf.DUMMYFUNCTION("""COMPUTED_VALUE"""),"Mar 2018") -> Mar 2018 | F30: =IFERROR(__xludf.DUMMYFUNCTION("""COMPUTED_VALUE"""),"Mar 2019") -> Mar 2019 | G30: =IFERROR(__xludf.DUMMYFUNCTION("""COMPUTED_VALUE"""),"Mar 2020") -> Mar 2020 | H30: =IFERROR(__xludf.DUMMYFUNCTION("""COMPUTED_VALUE"""),"Mar 2021") -> Mar 2021 | I30: =IFERROR(__xludf.DUMMYFUNCTION("""COMPUTED_VALUE"""),"Mar 2022") -> Mar 2022 | J30: =IFERROR(__xludf.DUMMYFUNCTION("""COMPUTED_VALUE"""),"Mar 2023") -> Mar 2023 | K30: =IFERROR(__xludf.DUMMYFUNCTION("""COMPUTED_VALUE"""),"Mar 2024") -> Mar 2024 | L30: =IFERROR(__xludf.DUMMYFUNCTION("""COMPUTED_VALUE"""),"Mar 2025") -> Mar 2025 | M30: =IFERROR(__xludf.DUMMYFUNCTION("""COMPUTED_VALUE"""),"Mar 2026") -> Mar 2026 | N30: =IFERROR(__xludf.DUMMYFUNCTION("""COMPUTED_VALUE"""),"TTM") -> TTM
A31: =IFERROR(__xludf.DUMMYFUNCTION("""COMPUTED_VALUE"""),"Sales +") -> Sales + | B31: =IFERROR(__xludf.DUMMYFUNCTION("""COMPUTED_VALUE"""),80.0) -> 80 | C31: =IFERROR(__xludf.DUMMYFUNCTION("""COMPUTED_VALUE"""),87.0) -> 87 | D31: =IFERROR(__xludf.DUMMYFUNCTION("""COMPUTED_VALUE"""),84.0) -> 84 | E31: =IFERROR(__xludf.DUMMYFUNCTION("""COMPUTED_VALUE"""),88.0) -> 88 | F31: =IFERROR(__xludf.DUMMYFUNCTION("""COMPUTED_VALUE"""),108.0) -> 108 | G31: =IFERROR(__xludf.DUMMYFUNCTION("""COMPUTED_VALUE"""),92.0) -> 92 | H31: =IFERROR(__xludf.DUMMYFUNCTION("""COMPUTED_VALUE"""),104.0) -> 104 | I31: =IFERROR(__xludf.DUMMYFUNCTION("""COMPUTED_VALUE"""),114.0) -> 114 | J31: =IFERROR(__xludf.DUMMYFUNCTION("""COMPUTED_VALUE"""),130.0) -> 130 | K31: =IFERROR(__xludf.DUMMYFUNCTION("""COMPUTED_VALUE"""),140.0) -> 140 | L31: =IFERROR(__xludf.DUMMYFUNCTION("""COMPUTED_VALUE"""),155.0) -> 155 | M31: =IFERROR(__xludf.DUMMYFUNCTION("""COMPUTED_VALUE"""),150.0) -> 150 | N31: =IFERROR(__xludf.DUMMYFUNCTION("""COMPUTED_VALUE"""),148.0) -> 148
A32: =IFERROR(__xludf.DUMMYFUNCTION("""COMPUTED_VALUE"""),"Expenses +") -> Expenses + | B32: =IFERROR(__xludf.DUMMYFUNCTION("""COMPUTED_VALUE"""),62.0) -> 62 | C32: =IFERROR(__xludf.DUMMYFUNCTION("""COMPUTED_VALUE"""),74.0) -> 74 | D32: =IFERROR(__xludf.DUMMYFUNCTION("""COMPUTED_VALUE"""),78.0) -> 78 | E32: =IFERROR(__xludf.DUMMYFUNCTION("""COMPUTED_VALUE"""),85.0) -> 85 | F32: =IFERROR(__xludf.DUMMYFUNCTION("""COMPUTED_VALUE"""),97.0) -> 97 | G32: =IFERROR(__xludf.DUMMYFUNCTION("""COMPUTED_VALUE"""),85.0) -> 85 | H32: =IFERROR(__xludf.DUMMYFUNCTION("""COMPUTED_VALUE"""),86.0) -> 86 | I32: =IFERROR(__xludf.DUMMYFUNCTION("""COMPUTED_VALUE"""),98.0) -> 98 | J32: =IFERROR(__xludf.DUMMYFUNCTION("""COMPUTED_VALUE"""),109.0) -> 109 | K32: =IFERROR(__xludf.DUMMYFUNCTION("""COMPUTED_VALUE"""),118.0) -> 118 | L32: =IFERROR(__xludf.DUMMYFUNCTION("""COMPUTED_VALUE"""),131.0) -> 131 | M32: =IFERROR(__xludf.DUMMYFUNCTION("""COMPUTED_VALUE"""),124.0) -> 124 | N32: =IFERROR(__xludf.DUMMYFUNCTION("""COMPUTED_VALUE"""),124.0) -> 124
A33: =IFERROR(__xludf.DUMMYFUNCTION("""COMPUTED_VALUE"""),"Operating Profit") -> Operating Profit | B33: =IFERROR(__xludf.DUMMYFUNCTION("""COMPUTED_VALUE"""),19.0) -> 19 | C33: =IFERROR(__xludf.DUMMYFUNCTION("""COMPUTED_VALUE"""),13.0) -> 13 | D33: =IFERROR(__xludf.DUMMYFUNCTION("""COMPUTED_VALUE"""),6.0) -> 6 | E33: =IFERROR(__xludf.DUMMYFUNCTION("""COMPUTED_VALUE"""),4.0) -> 4 | F33: =IFERROR(__xludf.DUMMYFUNCTION("""COMPUTED_VALUE"""),10.0) -> 10 | G33: =IFERROR(__xludf.DUMMYFUNCTION("""COMPUTED_VALUE"""),7.0) -> 7 | H33: =IFERROR(__xludf.DUMMYFUNCTION("""COMPUTED_VALUE"""),18.0) -> 18 | I33: =IFERROR(__xludf.DUMMYFUNCTION("""COMPUTED_VALUE"""),17.0) -> 17 | J33: =IFERROR(__xludf.DUMMYFUNCTION("""COMPUTED_VALUE"""),21.0) -> 21 | K33: =IFERROR(__xludf.DUMMYFUNCTION("""COMPUTED_VALUE"""),22.0) -> 22 | L33: =IFERROR(__xludf.DUMMYFUNCTION("""COMPUTED_VALUE"""),25.0) -> 25 | M33: =IFERROR(__xludf.DUMMYFUNCTION("""COMPUTED_VALUE"""),25.0) -> 25 | N33: =IFERROR(__xludf.DUMMYFUNCTION("""COMPUTED_VALUE"""),25.0) -> 25
A34: =IFERROR(__xludf.DUMMYFUNCTION("""COMPUTED_VALUE"""),"OPM %") -> OPM % | B34: =IFERROR(__xludf.DUMMYFUNCTION("""COMPUTED_VALUE"""),0.23) -> 0.23 | C34: =IFERROR(__xludf.DUMMYFUNCTION("""COMPUTED_VALUE"""),0.15) -> 0.15 | D34: =IFERROR(__xludf.DUMMYFUNCTION("""COMPUTED_VALUE"""),0.07) -> 0.07 | E34: =IFERROR(__xludf.DUMMYFUNCTION("""COMPUTED_VALUE"""),0.042) -> 0.042 | F34: =IFERROR(__xludf.DUMMYFUNCTION("""COMPUTED_VALUE"""),0.09) -> 0.09 | G34: =IFERROR(__xludf.DUMMYFUNCTION("""COMPUTED_VALUE"""),0.08) -> 0.08 | H34: =IFERROR(__xludf.DUMMYFUNCTION("""COMPUTED_VALUE"""),0.18) -> 0.18 | I34: =IFERROR(__xludf.DUMMYFUNCTION("""COMPUTED_VALUE"""),0.15) -> 0.15 | J34: =IFERROR(__xludf.DUMMYFUNCTION("""COMPUTED_VALUE"""),0.16) -> 0.16 | K34: =IFERROR(__xludf.DUMMYFUNCTION("""COMPUTED_VALUE"""),0.16) -> 0.16 | L34: =IFERROR(__xludf.DUMMYFUNCTION("""COMPUTED_VALUE"""),0.16) -> 0.16 | M34: =IFERROR(__xludf.DUMMYFUNCTION("""COMPUTED_VALUE"""),0.17) -> 0.17 | N34: =IFERROR(__xludf.DUMMYFUNCTION("""COMPUTED_VALUE"""),0.17) -> 0.17
A35: =IFERROR(__xludf.DUMMYFUNCTION("""COMPUTED_VALUE"""),"Other Income +") -> Other Income + | B35: =IFERROR(__xludf.DUMMYFUNCTION("""COMPUTED_VALUE"""),1.0) -> 1 | C35: =IFERROR(__xludf.DUMMYFUNCTION("""COMPUTED_VALUE"""),2.0) -> 2 | D35: =IFERROR(__xludf.DUMMYFUNCTION("""COMPUTED_VALUE"""),3.0) -> 3 | E35: =IFERROR(__xludf.DUMMYFUNCTION("""COMPUTED_VALUE"""),2.0) -> 2 | F35: =IFERROR(__xludf.DUMMYFUNCTION("""COMPUTED_VALUE"""),2.0) -> 2 | G35: =IFERROR(__xludf.DUMMYFUNCTION("""COMPUTED_VALUE"""),-58.0) -> -58 | H35: =IFERROR(__xludf.DUMMYFUNCTION("""COMPUTED_VALUE"""),3.0) -> 3 | I35: =IFERROR(__xludf.DUMMYFUNCTION("""COMPUTED_VALUE"""),3.0) -> 3 | J35: =IFERROR(__xludf.DUMMYFUNCTION("""COMPUTED_VALUE"""),4.0) -> 4 | K35: =IFERROR(__xludf.DUMMYFUNCTION("""COMPUTED_VALUE"""),7.0) -> 7 | L35: =IFERROR(__xludf.DUMMYFUNCTION("""COMPUTED_VALUE"""),5.0) -> 5 | M35: =IFERROR(__xludf.DUMMYFUNCTION("""COMPUTED_VALUE"""),3.0) -> 3 | N35: =IFERROR(__xludf.DUMMYFUNCTION("""COMPUTED_VALUE"""),3.0) -> 3
A36: =IFERROR(__xludf.DUMMYFUNCTION("""COMPUTED_VALUE"""),"Interest") -> Interest | B36: =IFERROR(__xludf.DUMMYFUNCTION("""COMPUTED_VALUE"""),0.0) -> 0 | C36: =IFERROR(__xludf.DUMMYFUNCTION("""COMPUTED_VALUE"""),0.0) -> 0 | D36: =IFERROR(__xludf.DUMMYFUNCTION("""COMPUTED_VALUE"""),0.0) -> 0 | E36: =IFERROR(__xludf.DUMMYFUNCTION("""COMPUTED_VALUE"""),0.0) -> 0 | F36: =IFERROR(__xludf.DUMMYFUNCTION("""COMPUTED_VALUE"""),1.0) -> 1 | G36: =IFERROR(__xludf.DUMMYFUNCTION("""COMPUTED_VALUE"""),2.0) -> 2 | H36: =IFERROR(__xludf.DUMMYFUNCTION("""COMPUTED_VALUE"""),1.0) -> 1 | I36: =IFERROR(__xludf.DUMMYFUNCTION("""COMPUTED_VALUE"""),0.0) -> 0 | J36: =IFERROR(__xludf.DUMMYFUNCTION("""COMPUTED_VALUE"""),1.0) -> 1 | K36: =IFERROR(__xludf.DUMMYFUNCTION("""COMPUTED_VALUE"""),0.0) -> 0 | L36: =IFERROR(__xludf.DUMMYFUNCTION("""COMPUTED_VALUE"""),1.0) -> 1 | M36: =IFERROR(__xludf.DUMMYFUNCTION("""COMPUTED_VALUE"""),1.0) -> 1 | N36: =IFERROR(__xludf.DUMMYFUNCTION("""COMPUTED_VALUE"""),0.0) -> 0
A37: =IFERROR(__xludf.DUMMYFUNCTION("""COMPUTED_VALUE"""),"Depreciation") -> Depreciation | B37: =IFERROR(__xludf.DUMMYFUNCTION("""COMPUTED_VALUE"""),2.0) -> 2 | C37: =IFERROR(__xludf.DUMMYFUNCTION("""COMPUTED_VALUE"""),2.0) -> 2 | D37: =IFERROR(__xludf.DUMMYFUNCTION("""COMPUTED_VALUE"""),1.0) -> 1 | E37: =IFERROR(__xludf.DUMMYFUNCTION("""COMPUTED_VALUE"""),1.0) -> 1 | F37: =IFERROR(__xludf.DUMMYFUNCTION("""COMPUTED_VALUE"""),2.0) -> 2 | G37: =IFERROR(__xludf.DUMMYFUNCTION("""COMPUTED_VALUE"""),6.0) -> 6 | H37: =IFERROR(__xludf.DUMMYFUNCTION("""COMPUTED_VALUE"""),6.0) -> 6 | I37: =IFERROR(__xludf.DUMMYFUNCTION("""COMPUTED_VALUE"""),5.0) -> 5 | J37: =IFERROR(__xludf.DUMMYFUNCTION("""COMPUTED_VALUE"""),4.0) -> 4 | K37: =IFERROR(__xludf.DUMMYFUNCTION("""COMPUTED_VALUE"""),4.0) -> 4 | L37: =IFERROR(__xludf.DUMMYFUNCTION("""COMPUTED_VALUE"""),5.0) -> 5 | M37: =IFERROR(__xludf.DUMMYFUNCTION("""COMPUTED_VALUE"""),4.0) -> 4 | N37: =IFERROR(__xludf.DUMMYFUNCTION("""COMPUTED_VALUE"""),4.0) -> 4
A38: =IFERROR(__xludf.DUMMYFUNCTION("""COMPUTED_VALUE"""),"Profit before tax") -> Profit before tax | B38: =IFERROR(__xludf.DUMMYFUNCTION("""COMPUTED_VALUE"""),18.0) -> 18 | C38: =IFERROR(__xludf.DUMMYFUNCTION("""COMPUTED_VALUE"""),14.0) -> 14 | D38: =IFERROR(__xludf.DUMMYFUNCTION("""COMPUTED_VALUE"""),7.0) -> 7 | E38: =IFERROR(__xludf.DUMMYFUNCTION("""COMPUTED_VALUE"""),4.0) -> 4 | F38: =IFERROR(__xludf.DUMMYFUNCTION("""COMPUTED_VALUE"""),10.0) -> 10 | G38: =IFERROR(__xludf.DUMMYFUNCTION("""COMPUTED_VALUE"""),-59.0) -> -59 | H38: =IFERROR(__xludf.DUMMYFUNCTION("""COMPUTED_VALUE"""),14.0) -> 14 | I38: =IFERROR(__xludf.DUMMYFUNCTION("""COMPUTED_VALUE"""),15.0) -> 15 | J38: =IFERROR(__xludf.DUMMYFUNCTION("""COMPUTED_VALUE"""),20.0) -> 20 | K38: =IFERROR(__xludf.DUMMYFUNCTION("""COMPUTED_VALUE"""),24.0) -> 24 | L38: =IFERROR(__xludf.DUMMYFUNCTION("""COMPUTED_VALUE"""),25.0) -> 25 | M38: =IFERROR(__xludf.DUMMYFUNCTION("""COMPUTED_VALUE"""),24.0) -> 24 | N38: =IFERROR(__xludf.DUMMYFUNCTION("""COMPUTED_VALUE"""),23.0) -> 23
A39: =IFERROR(__xludf.DUMMYFUNCTION("""COMPUTED_VALUE"""),"Tax %") -> Tax % | B39: =IFERROR(__xludf.DUMMYFUNCTION("""COMPUTED_VALUE"""),0.36) -> 0.36 | C39: =IFERROR(__xludf.DUMMYFUNCTION("""COMPUTED_VALUE"""),0.39) -> 0.39 | D39: =IFERROR(__xludf.DUMMYFUNCTION("""COMPUTED_VALUE"""),0.37) -> 0.37 | E39: =IFERROR(__xludf.DUMMYFUNCTION("""COMPUTED_VALUE"""),0.55) -> 0.55 | F39: =IFERROR(__xludf.DUMMYFUNCTION("""COMPUTED_VALUE"""),0.3) -> 0.3 | G39: =IFERROR(__xludf.DUMMYFUNCTION("""COMPUTED_VALUE"""),0.01) -> 0.01 | H39: =IFERROR(__xludf.DUMMYFUNCTION("""COMPUTED_VALUE"""),0.39) -> 0.39 | I39: =IFERROR(__xludf.DUMMYFUNCTION("""COMPUTED_VALUE"""),0.26) -> 0.26 | J39: =IFERROR(__xludf.DUMMYFUNCTION("""COMPUTED_VALUE"""),0.24) -> 0.24 | K39: =IFERROR(__xludf.DUMMYFUNCTION("""COMPUTED_VALUE"""),0.23) -> 0.23 | L39: =IFERROR(__xludf.DUMMYFUNCTION("""COMPUTED_VALUE"""),0.25) -> 0.25 | M39: =IFERROR(__xludf.DUMMYFUNCTION("""COMPUTED_VALUE"""),0.26) -> 0.26
A40: =IFERROR(__xludf.DUMMYFUNCTION("""COMPUTED_VALUE"""),"Net Profit +") -> Net Profit + | B40: =IFERROR(__xludf.DUMMYFUNCTION("""COMPUTED_VALUE"""),11.0) -> 11 | C40: =IFERROR(__xludf.DUMMYFUNCTION("""COMPUTED_VALUE"""),8.0) -> 8 | D40: =IFERROR(__xludf.DUMMYFUNCTION("""COMPUTED_VALUE"""),4.0) -> 4 | E40: =IFERROR(__xludf.DUMMYFUNCTION("""COMPUTED_VALUE"""),2.0) -> 2 | F40: =IFERROR(__xludf.DUMMYFUNCTION("""COMPUTED_VALUE"""),7.0) -> 7 | G40: =IFERROR(__xludf.DUMMYFUNCTION("""COMPUTED_VALUE"""),-59.0) -> -59 | H40: =IFERROR(__xludf.DUMMYFUNCTION("""COMPUTED_VALUE"""),9.0) -> 9 | I40: =IFERROR(__xludf.DUMMYFUNCTION("""COMPUTED_VALUE"""),11.0) -> 11 | J40: =IFERROR(__xludf.DUMMYFUNCTION("""COMPUTED_VALUE"""),15.0) -> 15 | K40: =IFERROR(__xludf.DUMMYFUNCTION("""COMPUTED_VALUE"""),18.0) -> 18 | L40: =IFERROR(__xludf.DUMMYFUNCTION("""COMPUTED_VALUE"""),19.0) -> 19 | M40: =IFERROR(__xludf.DUMMYFUNCTION("""COMPUTED_VALUE"""),17.0) -> 17 | N40: =IFERROR(__xludf.DUMMYFUNCTION("""COMPUTED_VALUE"""),17.0) -> 17
A41: =IFERROR(__xludf.DUMMYFUNCTION("""COMPUTED_VALUE"""),"EPS in Rs") -> EPS in Rs | B41: =IFERROR(__xludf.DUMMYFUNCTION("""COMPUTED_VALUE"""),3.67) -> 3.67 | C41: =IFERROR(__xludf.DUMMYFUNCTION("""COMPUTED_VALUE"""),2.6) -> 2.6 | D41: =IFERROR(__xludf.DUMMYFUNCTION("""COMPUTED_VALUE"""),1.39) -> 1.39 | E41: =IFERROR(__xludf.DUMMYFUNCTION("""COMPUTED_VALUE"""),0.6) -> 0.6 | F41: =IFERROR(__xludf.DUMMYFUNCTION("""COMPUTED_VALUE"""),2.25) -> 2.25 | G41: =IFERROR(__xludf.DUMMYFUNCTION("""COMPUTED_VALUE"""),-18.51) -> -18.51 | H41: =IFERROR(__xludf.DUMMYFUNCTION("""COMPUTED_VALUE"""),2.67) -> 2.67 | I41: =IFERROR(__xludf.DUMMYFUNCTION("""COMPUTED_VALUE"""),3.42) -> 3.42 | J41: =IFERROR(__xludf.DUMMYFUNCTION("""COMPUTED_VALUE"""),4.71) -> 4.71 | K41: =IFERROR(__xludf.DUMMYFUNCTION("""COMPUTED_VALUE"""),5.76) -> 5.76 | L41: =IFERROR(__xludf.DUMMYFUNCTION("""COMPUTED_VALUE"""),5.9) -> 5.9 | M41: =IFERROR(__xludf.DUMMYFUNCTION("""COMPUTED_VALUE"""),5.45) -> 5.45 | N41: =IFERROR(__xludf.DUMMYFUNCTION("""COMPUTED_VALUE"""),5.18) -> 5.18
A42: =IFERROR(__xludf.DUMMYFUNCTION("""COMPUTED_VALUE"""),"Dividend Payout %") -> Dividend Payout % | B42: =IFERROR(__xludf.DUMMYFUNCTION("""COMPUTED_VALUE"""),0.22) -> 0.22 | C42: =IFERROR(__xludf.DUMMYFUNCTION("""COMPUTED_VALUE"""),0.31) -> 0.31 | D42: =IFERROR(__xludf.DUMMYFUNCTION("""COMPUTED_VALUE"""),0.58) -> 0.58 | E42: =IFERROR(__xludf.DUMMYFUNCTION("""COMPUTED_VALUE"""),1.34) -> 1.34 | F42: =IFERROR(__xludf.DUMMYFUNCTION("""COMPUTED_VALUE"""),0.36) -> 0.36 | G42: =IFERROR(__xludf.DUMMYFUNCTION("""COMPUTED_VALUE"""),0.0) -> 0 | H42: =IFERROR(__xludf.DUMMYFUNCTION("""COMPUTED_VALUE"""),0.0) -> 0 | I42: =IFERROR(__xludf.DUMMYFUNCTION("""COMPUTED_VALUE"""),0.23) -> 0.23 | J42: =IFERROR(__xludf.DUMMYFUNCTION("""COMPUTED_VALUE"""),0.17) -> 0.17 | K42: =IFERROR(__xludf.DUMMYFUNCTION("""COMPUTED_VALUE"""),0.14) -> 0.14 | L42: =IFERROR(__xludf.DUMMYFUNCTION("""COMPUTED_VALUE"""),0.17) -> 0.17 | M42: =IFERROR(__xludf.DUMMYFUNCTION("""COMPUTED_VALUE"""),0.18) -> 0.18
B43: =row()+match("Borrowings +",A45:A54, 0)+1 -> 47 | C43: =row()+match("Total Assets",A45:A54, 0)+1 -> 54 | D43: =row()+match("Fixed Assets +",A45:A54, 0)+1 -> 50 | E43: =row()+match("CWIP",A45:A54, 0)+1 -> 51 | F43: =row()+match("Total Liabilities",A45:A54, 0)+1 -> 49 | G43: {=INDEX(44:44, 1, MAX(IF(44:44<>"", COLUMN(44:44), 0)))} -> Mar 2026 | H43: {=INDEX(56:56, 1, MAX(IF(56:56<>"", COLUMN(56:56), 0)))} -> Mar 2026
A44: =IFERROR(__xludf.DUMMYFUNCTION("query(IMPORTHTML($A$5,""table"",7),""SELECT *"",1)"),"") | B44: =IFERROR(__xludf.DUMMYFUNCTION("""COMPUTED_VALUE"""),"Mar 2015") -> Mar 2015 | C44: =IFERROR(__xludf.DUMMYFUNCTION("""COMPUTED_VALUE"""),"Mar 2016") -> Mar 2016 | D44: =IFERROR(__xludf.DUMMYFUNCTION("""COMPUTED_VALUE"""),"Mar 2017") -> Mar 2017 | E44: =IFERROR(__xludf.DUMMYFUNCTION("""COMPUTED_VALUE"""),"Mar 2018") -> Mar 2018 | F44: =IFERROR(__xludf.DUMMYFUNCTION("""COMPUTED_VALUE"""),"Mar 2019") -> Mar 2019 | G44: =IFERROR(__xludf.DUMMYFUNCTION("""COMPUTED_VALUE"""),"Mar 2020") -> Mar 2020 | H44: =IFERROR(__xludf.DUMMYFUNCTION("""COMPUTED_VALUE"""),"Mar 2021") -> Mar 2021 | I44: =IFERROR(__xludf.DUMMYFUNCTION("""COMPUTED_VALUE"""),"Mar 2022") -> Mar 2022 | J44: =IFERROR(__xludf.DUMMYFUNCTION("""COMPUTED_VALUE"""),"Mar 2023") -> Mar 2023 | K44: =IFERROR(__xludf.DUMMYFUNCTION("""COMPUTED_VALUE"""),"Mar 2024") -> Mar 2024 | L44: =IFERROR(__xludf.DUMMYFUNCTION("""COMPUTED_VALUE"""),"Mar 2025") -> Mar 2025 | M44: =IFERROR(__xludf.DUMMYFUNCTION("""COMPUTED_VALUE"""),"Mar 2026") -> Mar 2026
A45: =IFERROR(__xludf.DUMMYFUNCTION("""COMPUTED_VALUE"""),"Equity Capital") -> Equity Capital | B45: =IFERROR(__xludf.DUMMYFUNCTION("""COMPUTED_VALUE"""),25.0) -> 25 | C45: =IFERROR(__xludf.DUMMYFUNCTION("""COMPUTED_VALUE"""),25.0) -> 25 | D45: =IFERROR(__xludf.DUMMYFUNCTION("""COMPUTED_VALUE"""),25.0) -> 25 | E45: =IFERROR(__xludf.DUMMYFUNCTION("""COMPUTED_VALUE"""),25.0) -> 25 | F45: =IFERROR(__xludf.DUMMYFUNCTION("""COMPUTED_VALUE"""),25.0) -> 25 | G45: =IFERROR(__xludf.DUMMYFUNCTION("""COMPUTED_VALUE"""),25.0) -> 25 | H45: =IFERROR(__xludf.DUMMYFUNCTION("""COMPUTED_VALUE"""),25.0) -> 25 | I45: =IFERROR(__xludf.DUMMYFUNCTION("""COMPUTED_VALUE"""),25.0) -> 25 | ... K45: =IFERROR(__xludf.DUMMYFUNCTION("""COMPUTED_VALUE"""),25.0) -> 25 | L45: =IFERROR(__xludf.DUMMYFUNCTION("""COMPUTED_VALUE"""),32.0) -> 32 | M45: =IFERROR(__xludf.DUMMYFUNCTION("""COMPUTED_VALUE"""),32.0) -> 32
A46: =IFERROR(__xludf.DUMMYFUNCTION("""COMPUTED_VALUE"""),"Reserves") -> Reserves | B46: =IFERROR(__xludf.DUMMYFUNCTION("""COMPUTED_VALUE"""),139.0) -> 139 | C46: =IFERROR(__xludf.DUMMYFUNCTION("""COMPUTED_VALUE"""),165.0) -> 165 | D46: =IFERROR(__xludf.DUMMYFUNCTION("""COMPUTED_VALUE"""),172.0) -> 172 | E46: =IFERROR(__xludf.DUMMYFUNCTION("""COMPUTED_VALUE"""),167.0) -> 167 | F46: =IFERROR(__xludf.DUMMYFUNCTION("""COMPUTED_VALUE"""),170.0) -> 170 | G46: =IFERROR(__xludf.DUMMYFUNCTION("""COMPUTED_VALUE"""),104.0) -> 104 | H46: =IFERROR(__xludf.DUMMYFUNCTION("""COMPUTED_VALUE"""),115.0) -> 115 | I46: =IFERROR(__xludf.DUMMYFUNCTION("""COMPUTED_VALUE"""),150.0) -> 150 | J46: =IFERROR(__xludf.DUMMYFUNCTION("""COMPUTED_VALUE"""),166.0) -> 166 | K46: =IFERROR(__xludf.DUMMYFUNCTION("""COMPUTED_VALUE"""),196.0) -> 196 | L46: =IFERROR(__xludf.DUMMYFUNCTION("""COMPUTED_VALUE"""),228.0) -> 228 | M46: =IFERROR(__xludf.DUMMYFUNCTION("""COMPUTED_VALUE"""),272.0) -> 272
A47: =IFERROR(__xludf.DUMMYFUNCTION("""COMPUTED_VALUE"""),"Borrowings +") -> Borrowings + | B47: =IFERROR(__xludf.DUMMYFUNCTION("""COMPUTED_VALUE"""),0.0) -> 0 | C47: =IFERROR(__xludf.DUMMYFUNCTION("""COMPUTED_VALUE"""),0.0) -> 0 | D47: =IFERROR(__xludf.DUMMYFUNCTION("""COMPUTED_VALUE"""),1.0) -> 1 | E47: =IFERROR(__xludf.DUMMYFUNCTION("""COMPUTED_VALUE"""),0.0) -> 0 | F47: =IFERROR(__xludf.DUMMYFUNCTION("""COMPUTED_VALUE"""),0.0) -> 0 | G47: =IFERROR(__xludf.DUMMYFUNCTION("""COMPUTED_VALUE"""),13.0) -> 13 | H47: =IFERROR(__xludf.DUMMYFUNCTION("""COMPUTED_VALUE"""),26.0) -> 26 | I47: =IFERROR(__xludf.DUMMYFUNCTION("""COMPUTED_VALUE"""),8.0) -> 8 | J47: =IFERROR(__xludf.DUMMYFUNCTION("""COMPUTED_VALUE"""),6.0) -> 6 | K47: =IFERROR(__xludf.DUMMYFUNCTION("""COMPUTED_VALUE"""),2.0) -> 2 | L47: =IFERROR(__xludf.DUMMYFUNCTION("""COMPUTED_VALUE"""),7.0) -> 7 | M47: =IFERROR(__xludf.DUMMYFUNCTION("""COMPUTED_VALUE"""),4.0) -> 4
A48: =IFERROR(__xludf.DUMMYFUNCTION("""COMPUTED_VALUE"""),"Other Liabilities +") -> Other Liabilities + | B48: =IFERROR(__xludf.DUMMYFUNCTION("""COMPUTED_VALUE"""),56.0) -> 56 | C48: =IFERROR(__xludf.DUMMYFUNCTION("""COMPUTED_VALUE"""),42.0) -> 42 | D48: =IFERROR(__xludf.DUMMYFUNCTION("""COMPUTED_VALUE"""),43.0) -> 43 | E48: =IFERROR(__xludf.DUMMYFUNCTION("""COMPUTED_VALUE"""),44.0) -> 44 | F48: =IFERROR(__xludf.DUMMYFUNCTION("""COMPUTED_VALUE"""),44.0) -> 44 | G48: =IFERROR(__xludf.DUMMYFUNCTION("""COMPUTED_VALUE"""),42.0) -> 42 | H48: =IFERROR(__xludf.DUMMYFUNCTION("""COMPUTED_VALUE"""),41.0) -> 41 | I48: =IFERROR(__xludf.DUMMYFUNCTION("""COMPUTED_VALUE"""),46.0) -> 46 | J48: =IFERROR(__xludf.DUMMYFUNCTION("""COMPUTED_VALUE"""),46.0) -> 46 | K48: =IFERROR(__xludf.DUMMYFUNCTION("""COMPUTED_VALUE"""),52.0) -> 52 | L48: =IFERROR(__xludf.DUMMYFUNCTION("""COMPUTED_VALUE"""),54.0) -> 54 | M48: =IFERROR(__xludf.DUMMYFUNCTION("""COMPUTED_VALUE"""),62.0) -> 62
A49: =IFERROR(__xludf.DUMMYFUNCTION("""COMPUTED_VALUE"""),"Total Liabilities") -> Total Liabilities | B49: =IFERROR(__xludf.DUMMYFUNCTION("""COMPUTED_VALUE"""),219.0) -> 219 | C49: =IFERROR(__xludf.DUMMYFUNCTION("""COMPUTED_VALUE"""),231.0) -> 231 | D49: =IFERROR(__xludf.DUMMYFUNCTION("""COMPUTED_VALUE"""),240.0) -> 240 | E49: =IFERROR(__xludf.DUMMYFUNCTION("""COMPUTED_VALUE"""),236.0) -> 236 | F49: =IFERROR(__xludf.DUMMYFUNCTION("""COMPUTED_VALUE"""),239.0) -> 239 | G49: =IFERROR(__xludf.DUMMYFUNCTION("""COMPUTED_VALUE"""),184.0) -> 184 | H49: =IFERROR(__xludf.DUMMYFUNCTION("""COMPUTED_VALUE"""),207.0) -> 207 | I49: =IFERROR(__xludf.DUMMYFUNCTION("""COMPUTED_VALUE"""),229.0) -> 229 | J49: =IFERROR(__xludf.DUMMYFUNCTION("""COMPUTED_VALUE"""),243.0) -> 243 | K49: =IFERROR(__xludf.DUMMYFUNCTION("""COMPUTED_VALUE"""),276.0) -> 276 | L49: =IFERROR(__xludf.DUMMYFUNCTION("""COMPUTED_VALUE"""),322.0) -> 322 | M49: =IFERROR(__xludf.DUMMYFUNCTION("""COMPUTED_VALUE"""),370.0) -> 370
A50: =IFERROR(__xludf.DUMMYFUNCTION("""COMPUTED_VALUE"""),"Fixed Assets +") -> Fixed Assets + | B50: =IFERROR(__xludf.DUMMYFUNCTION("""COMPUTED_VALUE"""),92.0) -> 92 | C50: =IFERROR(__xludf.DUMMYFUNCTION("""COMPUTED_VALUE"""),91.0) -> 91 | D50: =IFERROR(__xludf.DUMMYFUNCTION("""COMPUTED_VALUE"""),90.0) -> 90 | E50: =IFERROR(__xludf.DUMMYFUNCTION("""COMPUTED_VALUE"""),97.0) -> 97 | F50: =IFERROR(__xludf.DUMMYFUNCTION("""COMPUTED_VALUE"""),101.0) -> 101 | G50: =IFERROR(__xludf.DUMMYFUNCTION("""COMPUTED_VALUE"""),51.0) -> 51 | H50: =IFERROR(__xludf.DUMMYFUNCTION("""COMPUTED_VALUE"""),38.0) -> 38 | I50: =IFERROR(__xludf.DUMMYFUNCTION("""COMPUTED_VALUE"""),38.0) -> 38 | J50: =IFERROR(__xludf.DUMMYFUNCTION("""COMPUTED_VALUE"""),36.0) -> 36 | K50: =IFERROR(__xludf.DUMMYFUNCTION("""COMPUTED_VALUE"""),33.0) -> 33 | L50: =IFERROR(__xludf.DUMMYFUNCTION("""COMPUTED_VALUE"""),38.0) -> 38 | M50: =IFERROR(__xludf.DUMMYFUNCTION("""COMPUTED_VALUE"""),33.0) -> 33
A51: =IFERROR(__xludf.DUMMYFUNCTION("""COMPUTED_VALUE"""),"CWIP") -> CWIP | B51: =IFERROR(__xludf.DUMMYFUNCTION("""COMPUTED_VALUE"""),0.0) -> 0 | C51: =IFERROR(__xludf.DUMMYFUNCTION("""COMPUTED_VALUE"""),0.0) -> 0 | D51: =IFERROR(__xludf.DUMMYFUNCTION("""COMPUTED_VALUE"""),0.0) -> 0 | E51: =IFERROR(__xludf.DUMMYFUNCTION("""COMPUTED_VALUE"""),0.0) -> 0 | F51: =IFERROR(__xludf.DUMMYFUNCTION("""COMPUTED_VALUE"""),0.0) -> 0 | G51: =IFERROR(__xludf.DUMMYFUNCTION("""COMPUTED_VALUE"""),0.0) -> 0 | H51: =IFERROR(__xludf.DUMMYFUNCTION("""COMPUTED_VALUE"""),0.0) -> 0 | I51: =IFERROR(__xludf.DUMMYFUNCTION("""COMPUTED_VALUE"""),0.0) -> 0 | ... M51: =IFERROR(__xludf.DUMMYFUNCTION("""COMPUTED_VALUE"""),0.0) -> 0
A52: =IFERROR(__xludf.DUMMYFUNCTION("""COMPUTED_VALUE"""),"Investments") -> Investments | B52: =IFERROR(__xludf.DUMMYFUNCTION("""COMPUTED_VALUE"""),0.0) -> 0 | C52: =IFERROR(__xludf.DUMMYFUNCTION("""COMPUTED_VALUE"""),0.0) -> 0 | D52: =IFERROR(__xludf.DUMMYFUNCTION("""COMPUTED_VALUE"""),0.0) -> 0 | E52: =IFERROR(__xludf.DUMMYFUNCTION("""COMPUTED_VALUE"""),8.0) -> 8 | F52: =IFERROR(__xludf.DUMMYFUNCTION("""COMPUTED_VALUE"""),14.0) -> 14 | G52: =IFERROR(__xludf.DUMMYFUNCTION("""COMPUTED_VALUE"""),0.0) -> 0 | H52: =IFERROR(__xludf.DUMMYFUNCTION("""COMPUTED_VALUE"""),0.0) -> 0 | I52: =IFERROR(__xludf.DUMMYFUNCTION("""COMPUTED_VALUE"""),0.0) -> 0 | J52: =IFERROR(__xludf.DUMMYFUNCTION("""COMPUTED_VALUE"""),0.0) -> 0 | K52: =IFERROR(__xludf.DUMMYFUNCTION("""COMPUTED_VALUE"""),0.0) -> 0 | L52: =IFERROR(__xludf.DUMMYFUNCTION("""COMPUTED_VALUE"""),0.0) -> 0 | M52: =IFERROR(__xludf.DUMMYFUNCTION("""COMPUTED_VALUE"""),56.0) -> 56
A53: =IFERROR(__xludf.DUMMYFUNCTION("""COMPUTED_VALUE"""),"Other Assets +") -> Other Assets + | B53: =IFERROR(__xludf.DUMMYFUNCTION("""COMPUTED_VALUE"""),127.0) -> 127 | C53: =IFERROR(__xludf.DUMMYFUNCTION("""COMPUTED_VALUE"""),140.0) -> 140 | D53: =IFERROR(__xludf.DUMMYFUNCTION("""COMPUTED_VALUE"""),150.0) -> 150 | E53: =IFERROR(__xludf.DUMMYFUNCTION("""COMPUTED_VALUE"""),130.0) -> 130 | F53: =IFERROR(__xludf.DUMMYFUNCTION("""COMPUTED_VALUE"""),125.0) -> 125 | G53: =IFERROR(__xludf.DUMMYFUNCTION("""COMPUTED_VALUE"""),133.0) -> 133 | H53: =IFERROR(__xludf.DUMMYFUNCTION("""COMPUTED_VALUE"""),169.0) -> 169 | I53: =IFERROR(__xludf.DUMMYFUNCTION("""COMPUTED_VALUE"""),191.0) -> 191 | J53: =IFERROR(__xludf.DUMMYFUNCTION("""COMPUTED_VALUE"""),207.0) -> 207 | K53: =IFERROR(__xludf.DUMMYFUNCTION("""COMPUTED_VALUE"""),243.0) -> 243 | L53: =IFERROR(__xludf.DUMMYFUNCTION("""COMPUTED_VALUE"""),284.0) -> 284 | M53: =IFERROR(__xludf.DUMMYFUNCTION("""COMPUTED_VALUE"""),280.0) -> 280
A54: =IFERROR(__xludf.DUMMYFUNCTION("""COMPUTED_VALUE"""),"Total Assets") -> Total Assets | B54: =IFERROR(__xludf.DUMMYFUNCTION("""COMPUTED_VALUE"""),219.0) -> 219 | C54: =IFERROR(__xludf.DUMMYFUNCTION("""COMPUTED_VALUE"""),231.0) -> 231 | D54: =IFERROR(__xludf.DUMMYFUNCTION("""COMPUTED_VALUE"""),240.0) -> 240 | E54: =IFERROR(__xludf.DUMMYFUNCTION("""COMPUTED_VALUE"""),236.0) -> 236 | F54: =IFERROR(__xludf.DUMMYFUNCTION("""COMPUTED_VALUE"""),239.0) -> 239 | G54: =IFERROR(__xludf.DUMMYFUNCTION("""COMPUTED_VALUE"""),184.0) -> 184 | H54: =IFERROR(__xludf.DUMMYFUNCTION("""COMPUTED_VALUE"""),207.0) -> 207 | I54: =IFERROR(__xludf.DUMMYFUNCTION("""COMPUTED_VALUE"""),229.0) -> 229 | J54: =IFERROR(__xludf.DUMMYFUNCTION("""COMPUTED_VALUE"""),243.0) -> 243 | K54: =IFERROR(__xludf.DUMMYFUNCTION("""COMPUTED_VALUE"""),276.0) -> 276 | L54: =IFERROR(__xludf.DUMMYFUNCTION("""COMPUTED_VALUE"""),322.0) -> 322 | M54: =IFERROR(__xludf.DUMMYFUNCTION("""COMPUTED_VALUE"""),370.0) -> 370
B55: =row()+match("Borrowings +",A57:A66, 0)+1 -> 59 | C55: =row()+match("Total Assets",A57:A66, 0)+1 -> 66 | D55: =row()+match("Fixed Assets +",A57:A66, 0)+1 -> 62 | E55: =row()+match("CWIP",A57:A66, 0)+1 -> 63 | F55: =row()+match("Total Liabilities",A57:A66, 0)+1 -> 61
A56: =IFERROR(__xludf.DUMMYFUNCTION("query(IMPORTHTML($B$5,""table"",7),""SELECT *"",1)"),"") | B56: =IFERROR(__xludf.DUMMYFUNCTION("""COMPUTED_VALUE"""),"Mar 2015") -> Mar 2015 | C56: =IFERROR(__xludf.DUMMYFUNCTION("""COMPUTED_VALUE"""),"Mar 2016") -> Mar 2016 | D56: =IFERROR(__xludf.DUMMYFUNCTION("""COMPUTED_VALUE"""),"Mar 2017") -> Mar 2017 | E56: =IFERROR(__xludf.DUMMYFUNCTION("""COMPUTED_VALUE"""),"Mar 2018") -> Mar 2018 | F56: =IFERROR(__xludf.DUMMYFUNCTION("""COMPUTED_VALUE"""),"Mar 2019") -> Mar 2019 | G56: =IFERROR(__xludf.DUMMYFUNCTION("""COMPUTED_VALUE"""),"Mar 2020") -> Mar 2020 | H56: =IFERROR(__xludf.DUMMYFUNCTION("""COMPUTED_VALUE"""),"Mar 2021") -> Mar 2021 | I56: =IFERROR(__xludf.DUMMYFUNCTION("""COMPUTED_VALUE"""),"Mar 2022") -> Mar 2022 | J56: =IFERROR(__xludf.DUMMYFUNCTION("""COMPUTED_VALUE"""),"Mar 2023") -> Mar 2023 | K56: =IFERROR(__xludf.DUMMYFUNCTION("""COMPUTED_VALUE"""),"Mar 2024") -> Mar 2024 | L56: =IFERROR(__xludf.DUMMYFUNCTION("""COMPUTED_VALUE"""),"Mar 2025") -> Mar 2025 | M56: =IFERROR(__xludf.DUMMYFUNCTION("""COMPUTED_VALUE"""),"Mar 2026") -> Mar 2026
A57: =IFERROR(__xludf.DUMMYFUNCTION("""COMPUTED_VALUE"""),"Equity Capital") -> Equity Capital | B57: =IFERROR(__xludf.DUMMYFUNCTION("""COMPUTED_VALUE"""),25.0) -> 25 | C57: =IFERROR(__xludf.DUMMYFUNCTION("""COMPUTED_VALUE"""),25.0) -> 25 | D57: =IFERROR(__xludf.DUMMYFUNCTION("""COMPUTED_VALUE"""),25.0) -> 25 | E57: =IFERROR(__xludf.DUMMYFUNCTION("""COMPUTED_VALUE"""),26.0) -> 26 | F57: =IFERROR(__xludf.DUMMYFUNCTION("""COMPUTED_VALUE"""),26.0) -> 26 | G57: =IFERROR(__xludf.DUMMYFUNCTION("""COMPUTED_VALUE"""),26.0) -> 26 | H57: =IFERROR(__xludf.DUMMYFUNCTION("""COMPUTED_VALUE"""),26.0) -> 26 | I57: =IFERROR(__xludf.DUMMYFUNCTION("""COMPUTED_VALUE"""),26.0) -> 26 | J57: =IFERROR(__xludf.DUMMYFUNCTION("""COMPUTED_VALUE"""),25.0) -> 25 | K57: =IFERROR(__xludf.DUMMYFUNCTION("""COMPUTED_VALUE"""),25.0) -> 25 | L57: =IFERROR(__xludf.DUMMYFUNCTION("""COMPUTED_VALUE"""),32.0) -> 32 | M57: =IFERROR(__xludf.DUMMYFUNCTION("""COMPUTED_VALUE"""),32.0) -> 32
A58: =IFERROR(__xludf.DUMMYFUNCTION("""COMPUTED_VALUE"""),"Reserves") -> Reserves | B58: =IFERROR(__xludf.DUMMYFUNCTION("""COMPUTED_VALUE"""),142.0) -> 142 | C58: =IFERROR(__xludf.DUMMYFUNCTION("""COMPUTED_VALUE"""),148.0) -> 148 | D58: =IFERROR(__xludf.DUMMYFUNCTION("""COMPUTED_VALUE"""),153.0) -> 153 | E58: =IFERROR(__xludf.DUMMYFUNCTION("""COMPUTED_VALUE"""),154.0) -> 154 | F58: =IFERROR(__xludf.DUMMYFUNCTION("""COMPUTED_VALUE"""),160.0) -> 160 | G58: =IFERROR(__xludf.DUMMYFUNCTION("""COMPUTED_VALUE"""),96.0) -> 96 | H58: =IFERROR(__xludf.DUMMYFUNCTION("""COMPUTED_VALUE"""),105.0) -> 105 | I58: =IFERROR(__xludf.DUMMYFUNCTION("""COMPUTED_VALUE"""),116.0) -> 116 | J58: =IFERROR(__xludf.DUMMYFUNCTION("""COMPUTED_VALUE"""),121.0) -> 121 | K58: =IFERROR(__xludf.DUMMYFUNCTION("""COMPUTED_VALUE"""),138.0) -> 138 | L58: =IFERROR(__xludf.DUMMYFUNCTION("""COMPUTED_VALUE"""),157.0) -> 157 | M58: =IFERROR(__xludf.DUMMYFUNCTION("""COMPUTED_VALUE"""),172.0) -> 172
A59: =IFERROR(__xludf.DUMMYFUNCTION("""COMPUTED_VALUE"""),"Borrowings +") -> Borrowings + | B59: =IFERROR(__xludf.DUMMYFUNCTION("""COMPUTED_VALUE"""),0.0) -> 0 | C59: =IFERROR(__xludf.DUMMYFUNCTION("""COMPUTED_VALUE"""),0.0) -> 0 | D59: =IFERROR(__xludf.DUMMYFUNCTION("""COMPUTED_VALUE"""),1.0) -> 1 | E59: =IFERROR(__xludf.DUMMYFUNCTION("""COMPUTED_VALUE"""),0.0) -> 0 | F59: =IFERROR(__xludf.DUMMYFUNCTION("""COMPUTED_VALUE"""),0.0) -> 0 | G59: =IFERROR(__xludf.DUMMYFUNCTION("""COMPUTED_VALUE"""),12.0) -> 12 | H59: =IFERROR(__xludf.DUMMYFUNCTION("""COMPUTED_VALUE"""),7.0) -> 7 | I59: =IFERROR(__xludf.DUMMYFUNCTION("""COMPUTED_VALUE"""),8.0) -> 8 | J59: =IFERROR(__xludf.DUMMYFUNCTION("""COMPUTED_VALUE"""),6.0) -> 6 | K59: =IFERROR(__xludf.DUMMYFUNCTION("""COMPUTED_VALUE"""),2.0) -> 2 | L59: =IFERROR(__xludf.DUMMYFUNCTION("""COMPUTED_VALUE"""),7.0) -> 7 | M59: =IFERROR(__xludf.DUMMYFUNCTION("""COMPUTED_VALUE"""),4.0) -> 4
A60: =IFERROR(__xludf.DUMMYFUNCTION("""COMPUTED_VALUE"""),"Other Liabilities +") -> Other Liabilities + | B60: =IFERROR(__xludf.DUMMYFUNCTION("""COMPUTED_VALUE"""),20.0) -> 20 | C60: =IFERROR(__xludf.DUMMYFUNCTION("""COMPUTED_VALUE"""),21.0) -> 21 | D60: =IFERROR(__xludf.DUMMYFUNCTION("""COMPUTED_VALUE"""),15.0) -> 15 | E60: =IFERROR(__xludf.DUMMYFUNCTION("""COMPUTED_VALUE"""),23.0) -> 23 | F60: =IFERROR(__xludf.DUMMYFUNCTION("""COMPUTED_VALUE"""),28.0) -> 28 | G60: =IFERROR(__xludf.DUMMYFUNCTION("""COMPUTED_VALUE"""),22.0) -> 22 | H60: =IFERROR(__xludf.DUMMYFUNCTION("""COMPUTED_VALUE"""),19.0) -> 19 | I60: =IFERROR(__xludf.DUMMYFUNCTION("""COMPUTED_VALUE"""),20.0) -> 20 | J60: =IFERROR(__xludf.DUMMYFUNCTION("""COMPUTED_VALUE"""),18.0) -> 18 | K60: =IFERROR(__xludf.DUMMYFUNCTION("""COMPUTED_VALUE"""),22.0) -> 22 | L60: =IFERROR(__xludf.DUMMYFUNCTION("""COMPUTED_VALUE"""),23.0) -> 23 | M60: =IFERROR(__xludf.DUMMYFUNCTION("""COMPUTED_VALUE"""),32.0) -> 32
A61: =IFERROR(__xludf.DUMMYFUNCTION("""COMPUTED_VALUE"""),"Total Liabilities") -> Total Liabilities | B61: =IFERROR(__xludf.DUMMYFUNCTION("""COMPUTED_VALUE"""),187.0) -> 187 | C61: =IFERROR(__xludf.DUMMYFUNCTION("""COMPUTED_VALUE"""),194.0) -> 194 | D61: =IFERROR(__xludf.DUMMYFUNCTION("""COMPUTED_VALUE"""),195.0) -> 195 | E61: =IFERROR(__xludf.DUMMYFUNCTION("""COMPUTED_VALUE"""),203.0) -> 203 | F61: =IFERROR(__xludf.DUMMYFUNCTION("""COMPUTED_VALUE"""),213.0) -> 213 | G61: =IFERROR(__xludf.DUMMYFUNCTION("""COMPUTED_VALUE"""),156.0) -> 156 | H61: =IFERROR(__xludf.DUMMYFUNCTION("""COMPUTED_VALUE"""),157.0) -> 157 | I61: =IFERROR(__xludf.DUMMYFUNCTION("""COMPUTED_VALUE"""),170.0) -> 170 | J61: =IFERROR(__xludf.DUMMYFUNCTION("""COMPUTED_VALUE"""),169.0) -> 169 | K61: =IFERROR(__xludf.DUMMYFUNCTION("""COMPUTED_VALUE"""),187.0) -> 187 | L61: =IFERROR(__xludf.DUMMYFUNCTION("""COMPUTED_VALUE"""),219.0) -> 219 | M61: =IFERROR(__xludf.DUMMYFUNCTION("""COMPUTED_VALUE"""),240.0) -> 240
A62: =IFERROR(__xludf.DUMMYFUNCTION("""COMPUTED_VALUE"""),"Fixed Assets +") -> Fixed Assets + | B62: =IFERROR(__xludf.DUMMYFUNCTION("""COMPUTED_VALUE"""),4.0) -> 4 | C62: =IFERROR(__xludf.DUMMYFUNCTION("""COMPUTED_VALUE"""),3.0) -> 3 | D62: =IFERROR(__xludf.DUMMYFUNCTION("""COMPUTED_VALUE"""),2.0) -> 2 | E62: =IFERROR(__xludf.DUMMYFUNCTION("""COMPUTED_VALUE"""),9.0) -> 9 | F62: =IFERROR(__xludf.DUMMYFUNCTION("""COMPUTED_VALUE"""),13.0) -> 13 | G62: =IFERROR(__xludf.DUMMYFUNCTION("""COMPUTED_VALUE"""),22.0) -> 22 | H62: =IFERROR(__xludf.DUMMYFUNCTION("""COMPUTED_VALUE"""),9.0) -> 9 | I62: =IFERROR(__xludf.DUMMYFUNCTION("""COMPUTED_VALUE"""),10.0) -> 10 | J62: =IFERROR(__xludf.DUMMYFUNCTION("""COMPUTED_VALUE"""),7.0) -> 7 | K62: =IFERROR(__xludf.DUMMYFUNCTION("""COMPUTED_VALUE"""),4.0) -> 4 | L62: =IFERROR(__xludf.DUMMYFUNCTION("""COMPUTED_VALUE"""),10.0) -> 10 | M62: =IFERROR(__xludf.DUMMYFUNCTION("""COMPUTED_VALUE"""),5.0) -> 5
A63: =IFERROR(__xludf.DUMMYFUNCTION("""COMPUTED_VALUE"""),"CWIP") -> CWIP | B63: =IFERROR(__xludf.DUMMYFUNCTION("""COMPUTED_VALUE"""),0.0) -> 0 | C63: =IFERROR(__xludf.DUMMYFUNCTION("""COMPUTED_VALUE"""),0.0) -> 0 | D63: =IFERROR(__xludf.DUMMYFUNCTION("""COMPUTED_VALUE"""),0.0) -> 0 | E63: =IFERROR(__xludf.DUMMYFUNCTION("""COMPUTED_VALUE"""),0.0) -> 0 | F63: =IFERROR(__xludf.DUMMYFUNCTION("""COMPUTED_VALUE"""),0.0) -> 0 | G63: =IFERROR(__xludf.DUMMYFUNCTION("""COMPUTED_VALUE"""),0.0) -> 0 | H63: =IFERROR(__xludf.DUMMYFUNCTION("""COMPUTED_VALUE"""),0.0) -> 0 | I63: =IFERROR(__xludf.DUMMYFUNCTION("""COMPUTED_VALUE"""),0.0) -> 0 | ... M63: =IFERROR(__xludf.DUMMYFUNCTION("""COMPUTED_VALUE"""),0.0) -> 0
A64: =IFERROR(__xludf.DUMMYFUNCTION("""COMPUTED_VALUE"""),"Investments") -> Investments | B64: =IFERROR(__xludf.DUMMYFUNCTION("""COMPUTED_VALUE"""),123.0) -> 123 | C64: =IFERROR(__xludf.DUMMYFUNCTION("""COMPUTED_VALUE"""),123.0) -> 123 | D64: =IFERROR(__xludf.DUMMYFUNCTION("""COMPUTED_VALUE"""),123.0) -> 123 | E64: =IFERROR(__xludf.DUMMYFUNCTION("""COMPUTED_VALUE"""),132.0) -> 132 | F64: =IFERROR(__xludf.DUMMYFUNCTION("""COMPUTED_VALUE"""),137.0) -> 137 | G64: =IFERROR(__xludf.DUMMYFUNCTION("""COMPUTED_VALUE"""),68.0) -> 68 | H64: =IFERROR(__xludf.DUMMYFUNCTION("""COMPUTED_VALUE"""),67.0) -> 67 | I64: =IFERROR(__xludf.DUMMYFUNCTION("""COMPUTED_VALUE"""),67.0) -> 67 | J64: =IFERROR(__xludf.DUMMYFUNCTION("""COMPUTED_VALUE"""),67.0) -> 67 | K64: =IFERROR(__xludf.DUMMYFUNCTION("""COMPUTED_VALUE"""),67.0) -> 67 | L64: =IFERROR(__xludf.DUMMYFUNCTION("""COMPUTED_VALUE"""),67.0) -> 67 | M64: =IFERROR(__xludf.DUMMYFUNCTION("""COMPUTED_VALUE"""),67.0) -> 67
A65: =IFERROR(__xludf.DUMMYFUNCTION("""COMPUTED_VALUE"""),"Other Assets +") -> Other Assets + | B65: =IFERROR(__xludf.DUMMYFUNCTION("""COMPUTED_VALUE"""),60.0) -> 60 | C65: =IFERROR(__xludf.DUMMYFUNCTION("""COMPUTED_VALUE"""),68.0) -> 68 | D65: =IFERROR(__xludf.DUMMYFUNCTION("""COMPUTED_VALUE"""),69.0) -> 69 | E65: =IFERROR(__xludf.DUMMYFUNCTION("""COMPUTED_VALUE"""),62.0) -> 62 | F65: =IFERROR(__xludf.DUMMYFUNCTION("""COMPUTED_VALUE"""),63.0) -> 63 | G65: =IFERROR(__xludf.DUMMYFUNCTION("""COMPUTED_VALUE"""),66.0) -> 66 | H65: =IFERROR(__xludf.DUMMYFUNCTION("""COMPUTED_VALUE"""),81.0) -> 81 | I65: =IFERROR(__xludf.DUMMYFUNCTION("""COMPUTED_VALUE"""),93.0) -> 93 | J65: =IFERROR(__xludf.DUMMYFUNCTION("""COMPUTED_VALUE"""),95.0) -> 95 | K65: =IFERROR(__xludf.DUMMYFUNCTION("""COMPUTED_VALUE"""),115.0) -> 115 | L65: =IFERROR(__xludf.DUMMYFUNCTION("""COMPUTED_VALUE"""),142.0) -> 142 | M65: =IFERROR(__xludf.DUMMYFUNCTION("""COMPUTED_VALUE"""),168.0) -> 168
A66: =IFERROR(__xludf.DUMMYFUNCTION("""COMPUTED_VALUE"""),"Total Assets") -> Total Assets | B66: =IFERROR(__xludf.DUMMYFUNCTION("""COMPUTED_VALUE"""),187.0) -> 187 | C66: =IFERROR(__xludf.DUMMYFUNCTION("""COMPUTED_VALUE"""),194.0) -> 194 | D66: =IFERROR(__xludf.DUMMYFUNCTION("""COMPUTED_VALUE"""),195.0) -> 195 | E66: =IFERROR(__xludf.DUMMYFUNCTION("""COMPUTED_VALUE"""),203.0) -> 203 | F66: =IFERROR(__xludf.DUMMYFUNCTION("""COMPUTED_VALUE"""),213.0) -> 213 | G66: =IFERROR(__xludf.DUMMYFUNCTION("""COMPUTED_VALUE"""),156.0) -> 156 | H66: =IFERROR(__xludf.DUMMYFUNCTION("""COMPUTED_VALUE"""),157.0) -> 157 | I66: =IFERROR(__xludf.DUMMYFUNCTION("""COMPUTED_VALUE"""),170.0) -> 170 | J66: =IFERROR(__xludf.DUMMYFUNCTION("""COMPUTED_VALUE"""),169.0) -> 169 | K66: =IFERROR(__xludf.DUMMYFUNCTION("""COMPUTED_VALUE"""),187.0) -> 187 | L66: =IFERROR(__xludf.DUMMYFUNCTION("""COMPUTED_VALUE"""),219.0) -> 219 | M66: =IFERROR(__xludf.DUMMYFUNCTION("""COMPUTED_VALUE"""),240.0) -> 240
A68: Ratio | B68: =iferror(B69/B70*100,"") -> 1.0810811 | C68: =iferror(C69/C70*100,"") -> 1.6666667 | D68: ratio> | E68: =IF(H43>G43,iferror(C68,B68),if(H43=G43,iferror(B68,C68),C68)) -> 1.0810811 | F68: =if(E68<=33, "Pass","Fail") -> Pass
A69: Borrowing | B69: {=INDEX(INDIRECT(B43 & ":" & B43), 1, MAX(IF(INDIRECT(B43 & ":" & B43)<>"", COLUMN(INDIRECT(B43 & ":" & B43)), 0)))} -> 4 | C69: {=INDEX(INDIRECT(B55 & ":" & B55), 1, MAX(IF(INDIRECT(B55 & ":" & B55)<>"", COLUMN(INDIRECT(B55 & ":" & B55)), 0)))} -> 4
A70: Total Asset | B70: {=INDEX(INDIRECT(C43 & ":" & C43), 1, MAX(IF(INDIRECT(C43 & ":" & C43)<>"", COLUMN(INDIRECT(C43 & ":" & C43)), 0)))} -> 370 | C70: {=INDEX(INDIRECT(C55 & ":" & C55), 1, MAX(IF(INDIRECT(C55 & ":" & C55)<>"", COLUMN(INDIRECT(C55 & ":" & C55)), 0)))} -> 240
A71: Illiquid Ratio | B71: =iferror(B72/B70*100,"") -> 8.9189189 | C71: =iferror(C72/C70*100,"") -> 2.0833333 | E71: =IF(H43>G43,iferror(C71,B71),if(H43=G43,iferror(B71,C71),C71)) -> 8.9189189 | F71: =if(E71>=20, "Pass","Fail") -> Fail
A72: Illiquid Asset | B72: =B73+B74+B77 -> 33 | C72: =C73+C74+C77 -> 5
A73: Fixed Asset | B73: {=INDEX(INDIRECT(D43 & ":" & D43), 1, MAX(IF(INDIRECT(D43 & ":" & D43)<>"", COLUMN(INDIRECT(D43 & ":" & D43)), 0)))} -> 33 | C73: {=INDEX(INDIRECT(D55 & ":" & D55), 1, MAX(IF(INDIRECT(D55 & ":" & D55)<>"", COLUMN(INDIRECT(D55 & ":" & D55)), 0)))} -> 5
A74: CWIP | B74: {=INDEX(INDIRECT(E43 & ":" & E43), 1, MAX(IF(INDIRECT(E43 & ":" & E43)<>"", COLUMN(INDIRECT(E43 & ":" & E43)), 0)))} -> 0 | C74: {=INDEX(INDIRECT(E55 & ":" & E55), 1, MAX(IF(INDIRECT(E55 & ":" & E55)<>"", COLUMN(INDIRECT(E55 & ":" & E55)), 0)))} -> 0
B75: //*[@id="ratios"]/div[2]/table/tbody/tr[2]/td[13]
B76: =IFERROR(__xludf.DUMMYFUNCTION("iferror(IMPORTXML(A$5,$B$75),0)"),0.0) -> 0 | C76: =IFERROR(__xludf.DUMMYFUNCTION("iferror(IMPORTXML(B$5,$B$75),0)"),0.0) -> 0
A77: Inventories | B77: =if(B2<>"",B2,D9*B76/365) -> 0 | C77: =if(B2<>"",B2,D28*C76/365) -> 0
A78: Total Liabilities | B78: {=iferror(INDEX(INDIRECT(F43 & ":" & F43), 1, MAX(IF(INDIRECT(F43 & ":" & F43)<>"", COLUMN(INDIRECT(F43 & ":" & F43)), 0))),"")} -> 370 | C78: {=iferror(INDEX(INDIRECT(F55 & ":" & F55), 1, MAX(IF(INDIRECT(F55 & ":" & F55)<>"", COLUMN(INDIRECT(F55 & ":" & F55)), 0))),"")} -> 240 | E78: liquidity | F78: =IF(H43>G43,iferror(C79,B79),if(H43=G43,iferror(B79,C79),C79)) -> -33 | H78: =if(F78<F80, "Pass", "Fail") -> Pass
A79: Liquid Asset | B79: =B70-B72-B78 -> -33 | C79: =C70-C72-C78 -> -5 | E79: mcap | F79: =IFERROR(__xludf.DUMMYFUNCTION("GOOGLEFINANCE(G79&"":""&A1,""marketcap"")/10000000"),543.22157) -> 543.22157 | G79: =if(ISNUMBER(A1),"BOM","NSE") -> NSE
B80: //*[@id="top-ratios"]/li[1]/span[2]/span | F80: =IFERROR(__xludf.DUMMYFUNCTION("IF(ISERROR(F79),IMPORTXML(B5,B80),F79)"),543.22157) -> 543.22157
A81: Marketcap
A84: beer | F84: industry | G84: //div[@class='flex flex-space-between']/div[1]/p/a[1] | H84: =IFERROR(__xludf.DUMMYFUNCTION("IMPORTXML($B$5,G84)"),"#REF!") -> #REF!
A85: liquor | F85: sector | G85: //div[@class='flex flex-space-between']/div[1]/p/a[2] | H85: =IFERROR(__xludf.DUMMYFUNCTION("IMPORTXML($B$5,G85)"),"Information Technology") -> Information Technology
A86: pork | F86: business | G86: /html/body/main/div[3]/div[3]/div[1]/div[1]/div[2]/p/text() | H86: =IFERROR(__xludf.DUMMYFUNCTION("IMPORTXML($B$5,G86) & iferror(VLOOKUP(Shariah!D3,list!A:B,2,0),"""")"),"Incorporated in 1991, Mindteck Ltd is in the business of rendering engineering and IT services") -> Incorporated in 1991, Mindteck Ltd is in the business of rendering engineering and IT services
A87: alcohol
A88: gambling
A89: betting | F89: Summary | G89: =IF(SUMPRODUCT(--ISNUMBER(SEARCH($A$84:$A$111, H86)))>0, "Fail", "Pass") -> Pass
A90: tobacco | F90: Industry | G90: =IF(SUMPRODUCT(--ISNUMBER(SEARCH($A$84:$A$113, H84)))>0, "Fail", "Pass") -> Pass
A91: cigar | F91: Sector | G91: =IF(SUMPRODUCT(--ISNUMBER(SEARCH($A$84:$A$113, H85)))>0, "Fail", "Pass") -> Pass
A92: cloning | F92: Business | G92: =IF(and(G89="Pass",G90="Pass",G91="Pass"),"Pass","Fail") -> Pass
A93: television | F93: Status | G93: =IF(AND(G92="Pass",G7<=5,E68<=33,E71>=20,F78<=F80), "Compliant","Non-Compliant") -> Non-Compliant
A94: advertising
A95: media
A96: bank
A97: insurance
A98: porn
A99: advertisment
A100: Breweries
A101: Distilleries
A102: club
A103: photo
A104: video
...

Sheet list
A1: Stock list | B1: Non-Shariah Business | E1: RELIANCE
A2: agi | B2: wine bottle manufacturer | E2: TCS
A3: atulauto | B3: Finance & banking Income | E3: HDFCBANK
A4: 526187 | B4: ritual/religious | C4: ashram | E4: ICICIBANK
A5: prajind | B5: wine factory maker | E5: HINDUNILVR
A6: GULPOLY | B6: Wine raw material provider | E6: INFY
A7: Infy | B7: Finance & banking Income | E7: HDFC
E8: ITC
E9: SBIN
E10: BHARTIARTL
E11: KOTAKBANK
E12: BAJFINANCE
E13: LICI
E14: LT
E15: HCLTECH
E16: ASIANPAINT
E17: AXISBANK
E18: MARUTI
E19: SUNPHARMA
... E2137: ZICOM

Sheet nse stock
A1: Reliance Industries Limited | B1: RELIANCE
A2: Tata Consultancy Services Limited | B2: TCS
A3: HDFC Bank Limited | B3: HDFCBANK
A4: ICICI Bank Limited | B4: ICICIBANK
A5: Hindustan Unilever Limited | B5: HINDUNILVR
A6: Infosys Limited | B6: INFY
A7: Housing Development Finance Corporation Limited | B7: HDFC
A8: ITC Limited | B8: ITC
A9: State Bank of India | B9: SBIN
A10: Bharti Airtel Limited | B10: BHARTIARTL
A11: Kotak Mahindra Bank Limited | B11: KOTAKBANK
A12: Bajaj Finance Limited | B12: BAJFINANCE
... A2137: Zicom Electronic Security Systems Limited | B2137: ZICOM
